asanak_api/__init__.py
asanak_api/actions.py
asanak_api/asanak.py
asanak_api/main.py
asanak_api/status.py
asanak_api-0.1.1.dist-info/METADATA
asanak_api-0.1.1.dist-info/WHEEL
asanak_api-0.1.1.dist-info/top_level.txt
asanak_api-0.1.1.dist-info/RECORD
