Metadata-Version: 2.4
Name: asanak-api
Version: 0.1.1
Summary: A Python API for Asanak
Author-email: Wahab Safi <wahab.safi3@gmail.com>
Project-URL: Homepage, https://github.com/wahabsafi/asanak-api
Classifier: Programming Language :: Python :: 3
Classifier: Programming Language :: Python :: 3.12
Classifier: License :: OSI Approved :: MIT License
Classifier: Operating System :: OS Independent
Requires-Python: >=3.12
Requires-Dist: requests>=2.32.3
